nlp_interpreter/__init__.py
nlp_interpreter/llm_classifier.py
nlp_interpreter/llm_processor.py
nlp_interpreter/llm_switcher.py
nlp_interpreter/schema_validator.py
nlp_interpreter-1.0.0.dist-info/LICENSE
nlp_interpreter-1.0.0.dist-info/METADATA
nlp_interpreter-1.0.0.dist-info/WHEEL
nlp_interpreter-1.0.0.dist-info/entry_points.txt
nlp_interpreter-1.0.0.dist-info/top_level.txt
nlp_interpreter-1.0.0.dist-info/RECORD
