Metadata-Version: 2.1
Name: nlp_interpreter
Version: 1.0.0
Summary: A package for translating Natural language using NLP processing with Ollama and Gemini into actions.
Author-email: Iyaad Luqman K <iyaadluq@gmail.com>
License: MIT License
Project-URL: Homepage, https://github.com/Iyaad-luqman/nlp_interpreter
Keywords: nlp,AI,language-processing
Classifier: License :: OSI Approved :: MIT License
Classifier: Programming Language :: Python
Classifier: Programming Language :: Python :: 3
Requires-Python: >=3.9
License-File: LICENSE
Requires-Dist: langchain-community
Requires-Dist: python-dotenv
Requires-Dist: google-generativeai
Requires-Dist: jsonschema
